wikt/__init__.py
wikt/__main__.py
wikt/fancyprint.py
wikt/utils.py
wikt_cli-0.0.2.dist-info/LICENSE
wikt_cli-0.0.2.dist-info/METADATA
wikt_cli-0.0.2.dist-info/WHEEL
wikt_cli-0.0.2.dist-info/entry_points.txt
wikt_cli-0.0.2.dist-info/top_level.txt
wikt_cli-0.0.2.dist-info/RECORD
